[
    {
      "id": "1",
      "firsttitle": "Toronto,",
      "lasttitle": "Canada",
      "subtitle": "Hurry! Get the Best Villa for you",
      "url": "https://templatemo.com/templates/templatemo_591_villa_agency/assets/images/banner-01.jpg"
    },
    {
      "id": "2",
      "firsttitle": "Melbourne,",
      "lasttitle": "Australia",
      "subtitle": "Hurry! Get the best villa in town",
      "url": "https://templatemo.com/templates/templatemo_591_villa_agency/assets/images/banner-02.jpg"
    },
    {
      "id": "3",
      "firsttitle": "Miami",
      "lasttitle": "South Florida",
      "subtitle":"Act Now! Get the highest level penthouse",
      "url": "https://templatemo.com/templates/templatemo_591_villa_agency/assets/images/banner-03.jpg"
    }
   
   
  ]